sockchat/__main__.py
sockchat/colors.py
sockchat/common.py
sockchat/loggers.py
sockchat/scratchpad.py
sockchat/ui_provider.py
sockchat/util.py
sockchat/network/client.py
sockchat/network/message.py
sockchat/network/message_channel.py
sockchat/network/server.py
sockchat-0.0.2.dist-info/LICENSE
sockchat-0.0.2.dist-info/METADATA
sockchat-0.0.2.dist-info/WHEEL
sockchat-0.0.2.dist-info/top_level.txt
sockchat-0.0.2.dist-info/RECORD
