Metadata-Version: 2.1
Name: sockchat
Version: 0.0.2
Summary: A socket chat
License: Copyright <YEAR> <COPYRIGHT HOLDER>        
Classifier: Programming Language :: Python :: 3
Classifier: License :: OSI Approved :: MIT License
Classifier: Operating System :: OS Independent
Requires-Python: >=3.9
License-File: LICENSE
